{"cameraMode":{"drawMode":0,"name":"Shaded","section":"Shading Mode"},"sceneLighting":false,"audioPlay":false,"sceneViewState":{"m_AlwaysRefresh":false,"showFog":true,"showSkybox":false,"showFlares":true,"showImageEffects":true,"showParticleSystems":true,"showVisualEffectGraphs":true,"m_FxEnabled":true},"in2DMode":false,"pivot":{"x":0.3020579218864441,"y":-0.4810953736305237,"z":1.5115165710449219},"rotation":{"x":-0.04405727609992027,"y":0.46134939789772036,"z":-0.023234253749251367,"w":-0.8862127661705017},"size":1.0888962745666505,"orthographic":false}